setup.py
timecost.py
timecost.egg-info/PKG-INFO
timecost.egg-info/SOURCES.txt
timecost.egg-info/dependency_links.txt
timecost.egg-info/top_level.txt